uv_monorepo_dependency_tool/__init__.py
uv_monorepo_dependency_tool/cli.py
uv_monorepo_dependency_tool/py.typed
uv_monorepo_dependency_tool-1.0.1.dist-info/METADATA
uv_monorepo_dependency_tool-1.0.1.dist-info/WHEEL
uv_monorepo_dependency_tool-1.0.1.dist-info/entry_points.txt
uv_monorepo_dependency_tool-1.0.1.dist-info/RECORD
