Metadata-Version: 2.4
Name: uv-monorepo-dependency-tool
Version: 1.0.1
Summary: A uv tool for facilitating the usage of more complex monorepo project structures by pinning version dependencies when building archives with local path dependencies to other uv projects within the same monorepo.
Author-email: Margaret Black <black_margaret@bah.com>
License-Expression: MIT
Classifier: License :: OSI Approved :: MIT License
Classifier: Programming Language :: Python :: 3.9
Classifier: Programming Language :: Python :: 3.10
Classifier: Programming Language :: Python :: 3.11
Classifier: Programming Language :: Python :: 3.12
Classifier: Programming Language :: Python :: 3.13
Requires-Python: >=3.9
Requires-Dist: click>=8.1.8
Requires-Dist: toml>=0.10.2
